ask_for_password/__init__.py
ask_for_password/ask_for_password.py
ask_for_password-0.0.3.dist-info/METADATA
ask_for_password-0.0.3.dist-info/WHEEL
ask_for_password-0.0.3.dist-info/top_level.txt
ask_for_password-0.0.3.dist-info/RECORD
