Metadata-Version: 2.1
Name: ask-for-password
Version: 0.0.3
Summary: A GUI interface to get an user and a password list as [user,pass].
Home-page: https://github.com/jeykun/AskForPassword.git
Author: Junior R. Ribeiro
Author-email: juniorribeiro2013@gmail.com
License: Free for non-commercial use
Keywords: GUI,Tkinter,Password,Interface
Platform: UNKNOWN
Classifier: Development Status :: 5 - Production/Stable
Classifier: Intended Audience :: Developers
Classifier: Topic :: Software Development :: User Interfaces
Classifier: License :: Free for non-commercial use
Classifier: Programming Language :: Python :: 3
Classifier: Programming Language :: Python :: 3.3
Classifier: Programming Language :: Python :: 3.4
Classifier: Programming Language :: Python :: 3.5
Classifier: Programming Language :: Python :: 3.6
Classifier: Programming Language :: Python :: 3.7
Requires-Dist: sh (>=1.11)
